qgates/__init__.py
qgates/gates.py
qgates/qfn.py
qgates/states.py
qgates-1.2.0.dist-info/LICENSE
qgates-1.2.0.dist-info/METADATA
qgates-1.2.0.dist-info/WHEEL
qgates-1.2.0.dist-info/top_level.txt
qgates-1.2.0.dist-info/RECORD
