Metadata-Version: 2.1
Name: qgates
Version: 1.2.0
Summary: Helper library for quantum matrix math
Home-page: https://github.com/a-poor/QGates
Author: Austin Poor
Author-email: austinpoor@gmail.com
License: UNKNOWN
Platform: UNKNOWN
Classifier: Programming Language :: Python :: 3.6
Classifier: Programming Language :: Python :: 3.7
Classifier: Programming Language :: Python :: 3.8
Classifier: License :: OSI Approved :: GNU General Public License v3 (GPLv3)
Classifier: Operating System :: OS Independent
Requires-Python: >=3.6
Requires-Dist: numpy
